csa_nemo_layer/__init__.py
csa_nemo_layer/async_helpers.py
csa_nemo_layer/classes.py
csa_nemo_layer/constants.py
csa_nemo_layer/helpers.py
csa_nemo_layer-0.0.8.dist-info/LICENSE
csa_nemo_layer-0.0.8.dist-info/METADATA
csa_nemo_layer-0.0.8.dist-info/WHEEL
csa_nemo_layer-0.0.8.dist-info/top_level.txt
csa_nemo_layer-0.0.8.dist-info/RECORD
