Metadata-Version: 2.1
Name: csa-nemo-layer
Version: 0.0.8
Summary: Shared libraries for CSA Lambdas
Author-email: Andrii Struk <andrii@struk.net.ua>
Project-URL: Homepage, https://github.com/struk77/csa_nemo_layer
Project-URL: Bug Tracker, https://github.com/struk77/csa_nemo_layer/issues
Classifier: Programming Language :: Python :: 3
Classifier: License :: OSI Approved :: MIT License
Classifier: Operating System :: OS Independent
Requires-Python: >=3.7
License-File: LICENSE
Requires-Dist: aioboto3
Requires-Dist: simplejson
Requires-Dist: aws-lambda-powertools
